[
    {
        "image_path": "./screenshots/original/screenshots/bird_0_0.30_3.0_1721600388.png",
        "bbox": {
            "x1": 1134.003173828125,
            "y1": 745.8085327148438,
            "x2": 1667.9271240234375,
            "y2": 968.0504760742188
        },
        "orig_shape": [
            1080,
            1920
        ]
    },
    {
        "image_path": "./screenshots/original/screenshots/bird_0_0.58_1.0_1721600396.png",
        "bbox": {
            "x1": 94.60537719726562,
            "y1": 731.8230590820312,
            "x2": 530.2123413085938,
            "y2": 995.173095703125
        },
        "orig_shape": [
            1080,
            1920
        ]
    },
    {
        "image_path": "./screenshots/original/screenshots/bird_0_0.64_5.0_1721600414.png",
        "bbox": {
            "x1": 881.5535278320312,
            "y1": 553.6817016601562,
            "x2": 1821.639892578125,
            "y2": 969.8966064453125
        },
        "orig_shape": [
            1080,
            1920
        ]
    }
]